MANIFEST.in
README.rst
setup.py
docs/HISTORY.txt
docs/INSTALL.txt
docs/LICENSE.GPL
docs/LICENSE.txt
docs/TODO.txt
unice/.DS_Store
unice/__init__.py
unice.portlet.focus.egg-info/PKG-INFO
unice.portlet.focus.egg-info/SOURCES.txt
unice.portlet.focus.egg-info/dependency_links.txt
unice.portlet.focus.egg-info/entry_points.txt
unice.portlet.focus.egg-info/namespace_packages.txt
unice.portlet.focus.egg-info/not-zip-safe
unice.portlet.focus.egg-info/requires.txt
unice.portlet.focus.egg-info/top_level.txt
unice/portlet/.DS_Store
unice/portlet/__init__.py
unice/portlet/focus/.DS_Store
unice/portlet/focus/__init__.py
unice/portlet/focus/configure.zcml
unice/portlet/focus/focusportlet.pt
unice/portlet/focus/focusportlet.py
unice/portlet/focus/vocabularies.py
unice/portlet/focus/browser/.DS_Store
unice/portlet/focus/browser/__init__.py
unice/portlet/focus/browser/configure.zcml
unice/portlet/focus/browser/stylesheets/styles.css
unice/portlet/focus/profiles/.DS_Store
unice/portlet/focus/profiles/default/cssregistry.xml
unice/portlet/focus/profiles/default/metadata.xml
unice/portlet/focus/profiles/default/portlets.xml
unice/portlet/focus/tests/__init__.py
unice/portlet/focus/tests/base.py
unice/portlet/focus/tests/test_portlet.py